efficientunet
