Metadata-Version: 1.2
Name: efficientunet
Version: 0.0.3
Summary: Keras Implementation of Unet with EfficientNet as encoder.
Home-page: https://github.com/zhoudaxia233/efficientunet
License: MIT
Keywords: unet-keras
Platform: UNKNOWN
Requires-Python: >=3.6
